{
  "props": {},
  "title": "Ex-Gratia Payments",
  "defaultActionLabel": "Submit",
  "fields": [
    {
      "validation": [
        "required",
        "isValidDate",
        "isBeforeToday"
      ],
      "props": {
        "visibilityConditions": [
          {
            "conditionPropertyName": "BusinessArea",
            "conditionPropertyValue": "HMPO"
          }
        ]
      },
      "component": "date",
      "name": "ExGratiaDateOfClaim",
      "label": "Date of Claim"
    },
    {
      "validation": [
        "required"
      ],
      "props": {
        "choices": "POGR_HMPO_EX_GRATIA_TYPE_OF_REFUND",
        "visibilityConditions": [
          {
            "conditionPropertyName": "BusinessArea",
            "conditionPropertyValue": "HMPO"
          }
        ]
      },
      "component": "dropdown",
      "name": "ExGratiaTypeOfRefund",
      "label": "Type of Refund"
    },
    {
      "validation": [
        "required"
      ],
      "props": {
        "choices": "POGR_HMPO_EX_GRATIA_REFUND_REASON",
        "visibilityConditions": [
          {
            "conditionPropertyName": "BusinessArea",
            "conditionPropertyValue": "HMPO"
          }
        ]
      },
      "component": "dropdown",
      "name": "ExGratiaPrimaryRefundReason",
      "label": "Primary Reason for Refund"
    },
    {
      "validation": [],
      "props": {
        "choices": "POGR_HMPO_EX_GRATIA_REFUND_REASON",
        "visibilityConditions": [
          {
            "conditionPropertyName": "BusinessArea",
            "conditionPropertyValue": "HMPO"
          }
        ]
      },
      "component": "dropdown",
      "name": "ExGratiaSecondRefundReason",
      "label": "Second Reason for Refund"
    },
    {
      "validation": [],
      "props": {
        "choices": "POGR_HMPO_EX_GRATIA_REFUND_REASON",
        "visibilityConditions": [
          {
            "conditionPropertyName": "BusinessArea",
            "conditionPropertyValue": "HMPO"
          }
        ]
      },
      "component": "dropdown",
      "name": "ExGratiaThirdRefundReason",
      "label": "Third Reason for Refund"
    },
    {
      "validation": [
        "required"
      ],
      "props": {
        "choices": "POGR_HMPO_EX_GRATIA_PAYMENT_METHOD",
        "visibilityConditions": [
          {
            "conditionPropertyName": "BusinessArea",
            "conditionPropertyValue": "HMPO"
          }
        ]
      },
      "component": "dropdown",
      "name": "ExGratiaPaymentMethod",
      "label": "Payment Method"
    },
    {
      "validation": [
        "required"
      ],
      "props": {
        "visibilityConditions": [
          {
            "conditionPropertyName": "BusinessArea",
            "conditionPropertyValue": "HMPO"
          }
        ]
      },
      "component": "text",
      "name": "ExGratiaPaymentReferenceNumber",
      "label": "Payment Reference Number"
    },
    {
      "validation": [],
      "props": {
        "choices": [
          {
            "label": "Yes",
            "value": "Yes"
          },
          {
            "label": "No",
            "value": "No"
          }
        ],
        "visibilityConditions": [
          {
            "conditionPropertyName": "BusinessArea",
            "conditionPropertyValue": "GRO"
          }
        ]
      },
      "component": "radio",
      "name": "ExGratiaRefundRequired",
      "label": "Refund Required"
    },
    {
      "validation": [],
      "props": {
        "choices": "GRO_EX_GRATIA_TYPE_OF_REFUND",
        "visibilityConditions": [
          {
            "conditionPropertyName": "BusinessArea",
            "conditionPropertyValue": "GRO"
          }
        ]
      },
      "component": "dropdown",
      "name": "ExGratiaTypeOfRefund",
      "label": "Type of Refund"
    },
    {
      "validation": [],
      "props": {
        "choices": "GRO_EX_GRATIA_PRIMARY_REFUND_REASON",
        "visibilityConditions": [
          {
            "conditionPropertyName": "BusinessArea",
            "conditionPropertyValue": "GRO"
          }
        ]
      },
      "component": "dropdown",
      "name": "ExGratiaPrimaryRefundReason",
      "label": "Primary Reason for Refund"
    },
    {
      "validation": [],
      "props": {
        "choices": "GRO_EX_GRATIA_SECONDARY_REFUND_REASON",
        "visibilityConditions": [
          {
            "conditionPropertyName": "BusinessArea",
            "conditionPropertyValue": "GRO"
          }
        ]
      },
      "component": "dropdown",
      "name": "ExGratiaSecondRefundReason",
      "label": "Secondary Reason for Refund"
    },
    {
      "validation": [
        "strictCurrency"
      ],
      "props": {
        "visibilityConditions": [
          {
            "conditionPropertyName": "BusinessArea",
            "conditionPropertyValue": "GRO"
          }
        ]
      },
      "component": "text",
      "name": "ExGratiaRefundAmount",
      "label": "Amount"
    },
    {
      "validation": [],
      "props": {
        "choices": "GRO_EX_GRATIA_PAYMENT_METHOD",
        "visibilityConditions": [
          {
            "conditionPropertyName": "BusinessArea",
            "conditionPropertyValue": "GRO"
          }
        ]
      },
      "component": "dropdown",
      "name": "ExGratiaPaymentMethod",
      "label": "Payment Method"
    },
    {
      "validation": [],
      "props": {
        "visibilityConditions": [
          {
            "conditionPropertyName": "BusinessArea",
            "conditionPropertyValue": "GRO"
          }
        ]
      },
      "component": "text",
      "name": "ExGratiaPaymentReferenceNumber",
      "label": "Payment Reference Number"
    },
    {
      "validation": [
        "required"
      ],
      "props": {
        "visibilityConditions": [
          {
            "function": "hasAnyValue",
            "conditionArgs": {
              "conditionPropertyName": "BusinessArea"
            }
          }
        ]
      },
      "component": "text",
      "name": "ExGratiaAuthorisedBy",
      "label": "Authorised By"
    },
    {
      "validation": [
        "required",
        "strictCurrency"
      ],
      "props": {
        "visibilityConditions": [
          {
            "function": "hasAnyValue",
            "conditionArgs": {
              "conditionPropertyName": "BusinessArea"
            }
          }
        ]
      },
      "component": "text",
      "name": "ExGratiaTotalAmount",
      "label": "Total Amount (GBP)"
    },
    {
      "validation": [],
      "props": {
        "visibilityConditions": [
          {
            "conditionPropertyName": "BusinessArea",
            "conditionPropertyValue": "GRO"
          }
        ]
      },
      "component": "text-area",
      "name": "ExGratiaAdditionalInformation",
      "label": "Additional Information"
    }
  ],
  "secondaryActions": [],
  "validation": "{}"
}
