{
  "props": {},
  "title": "Review complaint categories",
  "defaultActionLabel": "Finish",
  "fields": [
    {
      "component": "paragraph",
      "props": {
        "children": "Current categories are selected - recategorise if necessary before submitting."
      },
      "name": "categoryInset"
    },
    {
      "validation": [],
      "props": {},
      "component": "accordion",
      "name": "ServiceAccordion",
      "label": "Service"
    },
    {
      "validation": [],
      "props": {
        "choices": [
          {
            "label": "Admin / process error",
            "value": "AdminErr"
          }
        ]
      },
      "component": "checkbox",
      "name": "CatAdminErr",
      "label": ""
    },
    {
      "validation": [],
      "props": {
        "choices": [
          {
            "label": "Availability of service",
            "value": "Avail"
          }
        ]
      },
      "component": "checkbox",
      "name": "CatAvail",
      "label": ""
    },
    {
      "validation": [],
      "props": {
        "choices": [
          {
            "label": "Complaint handling",
            "value": "Handle"
          }
        ]
      },
      "component": "checkbox",
      "name": "CatHandle",
      "label": ""
    },
    {
      "validation": [],
      "props": {
        "choices": [
          {
            "label": "Delay",
            "value": "Delay"
          }
        ]
      },
      "component": "checkbox",
      "name": "CatDelay",
      "label": ""
    },
    {
      "validation": [],
      "props": {
        "choices": [
          {
            "label": "Physical environment",
            "value": "PhysEnv"
          }
        ]
      },
      "component": "checkbox",
      "name": "CatPhysEnv",
      "label": ""
    },
    {
      "validation": [],
      "props": {
        "choices": [
          {
            "label": "Poor communication",
            "value": "PoorComm"
          }
        ]
      },
      "component": "checkbox",
      "name": "CatPoorComm",
      "label": ""
    },
    {
      "validation": [],
      "props": {
        "choices": [
          {
            "label": "Property or documents - lost",
            "value": "Lost"
          }
        ]
      },
      "component": "checkbox",
      "name": "CatLost",
      "label": ""
    },
    {
      "validation": [],
      "props": {
        "choices": [
          {
            "label": "Property or documents - stolen",
            "value": "Stolen"
          }
        ]
      },
      "component": "checkbox",
      "name": "CatStolen",
      "label": ""
    },
    {
      "validation": [],
      "props": {
        "choices": [
          {
            "label": "Property or documents - withheld",
            "value": "Withheld"
          }
        ]
      },
      "component": "checkbox",
      "name": "CatWithheld",
      "label": ""
    },
    {
      "validation": [],
      "props": {
        "choices": [
          {
            "label": "Provision for minors",
            "value": "ProvMinor"
          }
        ]
      },
      "component": "checkbox",
      "name": "CatProvMinor",
      "label": ""
    },
    {
      "validation": [],
      "props": {
        "choices": [
          {
            "label": "Wrong information",
            "value": "WrongInfo"
          }
        ]
      },
      "component": "checkbox",
      "name": "CatWrongInfo",
      "label": ""
    },
    {
      "validation": [],
      "props": {},
      "component": "accordion",
      "label": "Serious and minor"
    },
    {
      "validation": [],
      "props": {
        "choices": [
          {
            "label": "Detainee on detainee",
            "value": "DetOnDet"
          }
        ]
      },
      "component": "checkbox",
      "name": "CatDetOnDet",
      "label": ""
    },
    {
      "validation": [],
      "props": {
        "choices": [
          {
            "label": "Other unprofessionalism",
            "value": "OtherUnprof"
          }
        ]
      },
      "component": "checkbox",
      "name": "CatOtherUnprof",
      "label": ""
    },
    {
      "validation": [],
      "props": {
        "choices": [
          {
            "label": "Rudeness",
            "value": "Rude"
          }
        ]
      },
      "component": "checkbox",
      "name": "CatRude",
      "label": ""
    },
    {
      "validation": [],
      "props": {
        "choices": [
          {
            "label": "Unfair treatment",
            "value": "Unfair"
          }
        ]
      },
      "component": "checkbox",
      "name": "CatUnfair",
      "label": ""
    },
    {
      "validation": [],
      "props": {},
      "component": "accordion",
      "label": "Serious"
    },
    {
      "validation": [],
      "props": {
        "choices": [
          {
            "label": "Assault",
            "value": "Assault"
          }
        ]
      },
      "component": "checkbox",
      "name": "CatAssault",
      "label": ""
    },
    {
      "validation": [],
      "props": {
        "choices": [
          {
            "label": "Fraud / corruption",
            "value": "Fraud"
          }
        ]
      },
      "component": "checkbox",
      "name": "CatFraud",
      "label": ""
    },
    {
      "validation": [],
      "props": {
        "choices": [
          {
            "label": "Racism / discrimination",
            "value": "Racism"
          }
        ]
      },
      "component": "checkbox",
      "name": "CatRacism",
      "label": ""
    },
    {
      "validation": [],
      "props": {
        "choices": [
          {
            "label": "Sexual assault",
            "value": "SexAssault"
          }
        ]
      },
      "component": "checkbox",
      "name": "CatSexAssault",
      "label": ""
    },
    {
      "validation": [],
      "props": {
        "choices": [
          {
            "label": "Theft",
            "value": "Theft"
          }
        ]
      },
      "component": "checkbox",
      "name": "CatTheft",
      "label": ""
    },
    {
      "validation": [],
      "props": {},
      "component": "accordion-end"
    }
  ],
  "secondaryActions": [
    {
      "validation": [],
      "props": {},
      "component": "backButton",
      "name": "backButton",
      "label": "Back"
    }
  ],
  "validation": "{\"linkTo\": \"ServiceAccordion\", \"message\": \"Select at least one complaint category option\", \"options\": [\"CatAdminErr\", \"CatAvail\", \"CatDelay\", \"CatPhysEnv\", \"CatPoorComm\", \"CatLost\", \"CatStolen\", \"CatWithheld\", \"CatCCProvMinor\", \"CatWrongInfo\", \"CatHandle\", \"CatRude\", \"CatUnfair\", \"CatOtherUnprof\", \"CatDetOnDet\", \"CatTheft\", \"CatAssault\", \"CatSexAssault\", \"CatFraud\", \"CatRacism\"], \"validator\": \"oneOf\"}"
}
