{
  "props": {},
  "title": "Eligibility Failure Confirmation",
  "defaultActionLabel": "Continue",
  "fields": [
    {
      "validation": [],
      "props": {
        "choices": [
          {
            "label": "Yes",
            "value": "Yes"
          },
          {
            "label": "No",
            "value": "No"
          }
        ],
        "disabled": true
      },
      "component": "radio",
      "name": "IdentityConfirmed",
      "label": "Can you confirm the claimant's identity?"
    },
    {
      "validation": [],
      "props": {
        "choices": [
          {
            "label": "Yes",
            "value": "Yes"
          },
          {
            "label": "No",
            "value": "No"
          }
        ],
        "disabled": true
      },
      "component": "radio",
      "name": "EligibilityConfirmed",
      "label": "Can you confirm the claimant's eligibility?"
    },
    {
      "validation": [],
      "props": {
        "choices": "S_WCS_ELIG_REJ_REASON"
      },
      "component": "mapped-text",
      "name": "EligibilityRejReason",
      "label": "Why is the claim not eligible?"
    },
    {
      "validation": [
        "required"
      ],
      "props": {
        "choices": [
          {
            "label": "Yes - close the claim",
            "value": "Yes"
          },
          {
            "label": "No",
            "value": "No"
          }
        ]
      },
      "component": "radio",
      "name": "EligibilityFailConfirm",
      "label": "The claimant is not eligible. Close the claim?"
    }
  ],
  "secondaryActions": [],
  "validation": "{}"
}
