{
  "props": {},
  "title": "Additional details",
  "defaultActionLabel": "Continue",
  "fields": [
    {
      "validation": [],
      "props": {
        "choices": "COUNTRIES_CURRENT"
      },
      "component": "dropdown",
      "name": "ComplainantNationality",
      "label": "Complainant's nationality"
    },
    {
      "validation": [],
      "props": {},
      "component": "text",
      "name": "PrevCompRef",
      "label": "Previous complaint reference"
    },
    {
      "validation": [],
      "props": {},
      "component": "text",
      "name": "ComplainantHORef",
      "label": "Home Office reference"
    },
    {
      "validation": [],
      "props": {},
      "component": "text",
      "name": "ComplainantPortRef",
      "label": "Port reference"
    },
    {
      "validation": [],
      "props": {},
      "component": "text",
      "name": "3rdPartyRef",
      "label": "Third party reference"
    },
    {
      "validation": [],
      "props": {},
      "component": "text",
      "name": "ComplainantCompanyName",
      "label": "Company name"
    }
  ],
  "secondaryActions": [
    {
      "validation": [],
      "props": {},
      "component": "backButton",
      "name": "backButton",
      "label": "Back"
    }
  ],
  "validation": "{}"
}
